cz_flexiv.py
cz_flexiv-0.1.1.dist-info/WHEEL
cz_flexiv-0.1.1.dist-info/METADATA
cz_flexiv-0.1.1.dist-info/RECORD
