Metadata-Version: 2.1
Name: cz-flexiv
Version: 0.1.1
Summary: 
Author: yunpeng.zhan
Author-email: yunpeng.zhan@flexiv.com
Requires-Python: >=3.7,<4.0
Classifier: Programming Language :: Python :: 3
Classifier: Programming Language :: Python :: 3.10
Classifier: Programming Language :: Python :: 3.7
Classifier: Programming Language :: Python :: 3.8
Classifier: Programming Language :: Python :: 3.9
Requires-Dist: commitizen (>=2.27.1,<3.0.0)
Requires-Dist: requests (>=2.28.1,<3.0.0)
